{
  "cmd": "SEND_GIFT",
  "data": {
    "giftName": "节奏风暴",
    "num": 1,
    "uname": "爱上熹",
    "rcost": 569788,
    "uid": 230845505,
    "top_list": [
      {
        "uid": 288348879,
        "uname": "我爱我家一生",
        "face": "http://i1.hdslb.com/bfs/face/dd52e4f2dfe881751816e45522f504f10458b514.jpg",
        "rank": 1,
        "score": 1852300,
        "guard_level": 0,
        "isSelf": 0
      },
      {
        "uid": 287551243,
        "uname": "熹上城的专属天使菲",
        "face": "http://i1.hdslb.com/bfs/face/c3ef04ba6c267c41067cd7708b7abd60c0c5c49f.jpg",
        "rank": 2,
        "score": 1245200,
        "guard_level": 3,
        "isSelf": 0
      },
      {
        "uid": 32416351,
        "uname": "镜子。。",
        "face": "http://i1.hdslb.com/bfs/face/08c54c2c97434811a99e9d070d621ccbb5d3f2c4.jpg",
        "rank": 3,
        "score": 332862,
        "guard_level": 3,
        "isSelf": 0
      }
    ],
    "timestamp": 1520992553,
    "giftId": 39,
    "giftType": 0,
    "action": "赠送",
    "super": 1,
    "super_gift_num": 1,
    "price": 100000,
    "rnd": "1980508331",
    "newMedal": 0,
    "newTitle": 0,
    "medal": {
      "medalId": "95723",
      "medalName": "布丁诶",
      "level": 1
    },
    "title": "",
    "beatId": "4",
    "biz_source": "live",
    "metadata": "",
    "remain": 0,
    "gold": 88570,
    "silver": 127492,
    "eventScore": 0,
    "eventNum": 0,
    "smalltv_msg": [],
    "specialGift": {
      "id": "316221038798",
      "time": 90,
      "hadJoin": 0,
      "num": 1,
      "content": "你们城里人真会玩",
      "action": "start",
      "storm_gif": "http://static.hdslb.com/live-static/live-room/images/gift-section/mobilegift/2/jiezou.gif?2017011901"
    },
    "notice_msg": [],
    "capsule": {
      "normal": {
        "coin": 166,
        "change": 10,
        "progress": {
          "now": 3630,
          "max": 10000
        }
      },
      "colorful": {
        "coin": 2,
        "change": 0,
        "progress": {
          "now": 0,
          "max": 5000
        }
      },
      "move": 1
    },
    "addFollow": 0,
    "effect_block": 0,
    "coin_type": "gold",
    "total_coin": 100000
  }
}
